[
  {
    "id": 8,
    "question": "First question - list 3",
    "options": [ 
      "First option",
      "Second option"
    ]
  },
  {
    "id": 9,
    "question": "Second question - list 3",
    "options": [ 
      "First option",
      "Second option"
    ]
  },
  {
    "id": 12,
    "question": "Third question - list 3",
    "options": [ 
      "First option",
      "Second option"
    ]
  },
  {
    "id": 23,
    "question": "Third question - list 3",
    "options": [ 
      "First option",
      "Second option",
      "Third option",
      "Fourth option",
      "Fifth option",
      "Sixth option",
      "Seventh option",
      "Eighth option"
    ]
  },
  {
    "id": 29,
    "question": "Fourth question - list 3",
    "options": [ 
      "First option",
      "Second option",
      "Third option",
      "Fourth option",
      "Fifth option",
      "Sixth option"
    ]
  },
  {
    "id": 31,
    "question": "Fourth question - list 3",
    "options": [ 
      "First option",
      "Second option"
    ]
  }

]